font_msyh/__init__.py
font_msyh/files/msyh.ttf
font_msyh-0.0.1.dist-info/LICENSE.txt
font_msyh-0.0.1.dist-info/METADATA
font_msyh-0.0.1.dist-info/WHEEL
font_msyh-0.0.1.dist-info/entry_points.txt
font_msyh-0.0.1.dist-info/top_level.txt
font_msyh-0.0.1.dist-info/RECORD
