Metadata-Version: 2.1
Name: font-msyh
Version: 0.0.1
Summary: font_msyh font
Home-page: https://github.com/breezecloud/font-msyh
Author: luping
Author-email: luping.sh@chinatelecom.cn
License: Apache 2.0
Keywords: msyh Font
Classifier: Development Status :: 5 - Production/Stable
Classifier: Operating System :: POSIX :: Linux
Classifier: License :: OSI Approved :: Apache Software License
Classifier: Intended Audience :: Developers
Classifier: Programming Language :: Python :: 2.6
Classifier: Programming Language :: Python :: 2.7
Classifier: Programming Language :: Python :: 3
Classifier: Topic :: Software Development
Classifier: Topic :: Text Processing :: Fonts
License-File: LICENSE.txt
